README.md
setup.py
empyric/__init__.py
empyric/adapters.py
empyric/experiment.py
empyric/graphics.py
empyric/instruments.py
empyric/collection/__init__.py
empyric/collection/barometers.py
empyric/collection/controllers.py
empyric/collection/humans.py
empyric/collection/instrument.py
empyric/collection/multimeters.py
empyric/collection/scopes.py
empyric/collection/sourcemeters.py
empyric/collection/spectrometers.py
empyric/collection/supplies.py
empyric/collection/thermometers.py
empyric/collection/virtual.py
empyric_dmerthe.egg-info/PKG-INFO
empyric_dmerthe.egg-info/SOURCES.txt
empyric_dmerthe.egg-info/dependency_links.txt
empyric_dmerthe.egg-info/entry_points.txt
empyric_dmerthe.egg-info/top_level.txt