Metadata-Version: 2.1
Name: empyric-dmerthe
Version: 0.1
Summary: A package for experiment automation
Home-page: https://github.com/dmerthe/empyric
Author: Daniel Merthe
Author-email: dmerthe@gmail.com
License: UNKNOWN
Platform: UNKNOWN
Classifier: Programming Language :: Python :: 3
Classifier: License :: OSI Approved :: MIT License
Classifier: Operating System :: OS Independent
Requires-Python: >=3.6
